HISTORY.rst
LICENSE
MANIFEST.in
README.md
setup.py
redisqueue/__init__.py
redisqueue/mock.py
redisqueue.egg-info/PKG-INFO
redisqueue.egg-info/SOURCES.txt
redisqueue.egg-info/dependency_links.txt
redisqueue.egg-info/not-zip-safe
redisqueue.egg-info/requires.txt
redisqueue.egg-info/top_level.txt