Metadata-Version: 1.1
Name: redisqueue
Version: 0.1.4
Summary: Simple Redis Queue Library
Home-page: https://github.com/DevKeh/redisqueue
Author: Jeff Kehler
Author-email: jeffrey.kehler@gmail.com
License: MIT
Keywords: redis queue
Platform: UNKNOWN
Classifier: Development Status :: 4 - Beta
Classifier: Intended Audience :: Developers
Classifier: License :: OSI Approved :: MIT License
Classifier: Operating System :: MacOS :: MacOS X
Classifier: Operating System :: POSIX
Classifier: Operating System :: Microsoft :: Windows
Classifier: Programming Language :: Python
Classifier: Programming Language :: Python :: 2.6
Classifier: Programming Language :: Python :: 2.7
Classifier: Programming Language :: Python :: 3.2
Classifier: Programming Language :: Python :: 3.3
Classifier: Programming Language :: Python :: 3.4
Classifier: Topic :: Utilities
Classifier: Topic :: Software Development :: Libraries :: Python Modules
